quart_saml.py
Quart_SAML-0.1.0.dist-info/LICENSE.txt
Quart_SAML-0.1.0.dist-info/METADATA
Quart_SAML-0.1.0.dist-info/WHEEL
Quart_SAML-0.1.0.dist-info/top_level.txt
Quart_SAML-0.1.0.dist-info/RECORD
