Metadata-Version: 2.1
Name: Quart-SAML
Version: 0.1.0
Summary: Quart SAML integration
Home-page: https://github.com/nojha95/quart_saml
Author: Nikhil Ojha
Author-email: nikhilojha1895@gmail.com
License: UNKNOWN
Platform: UNKNOWN
Requires-Python: >=3.8
License-File: LICENSE.txt
Requires-Dist: blinker (>=1.1)
Requires-Dist: httpx (>=0.17.0)
Requires-Dist: pysaml2 (>=6.5.0)
Requires-Dist: quart (>=0.12.0)
